setup.py
unimate.py
unimate.egg-info/PKG-INFO
unimate.egg-info/SOURCES.txt
unimate.egg-info/dependency_links.txt
unimate.egg-info/top_level.txt