Metadata-Version: 1.0
Name: unimate
Version: 1.0
Summary: Python Unimate client
Home-page: UNKNOWN
Author: Smarkets
Author-email: UNKNOWN
License: MIT
Platform: UNKNOWN
